AUTHORS.rst
LICENSE
MANIFEST.in
README.rst
setup.py
django_geventpool/__init__.py
django_geventpool/utils.py
django_geventpool.egg-info/PKG-INFO
django_geventpool.egg-info/SOURCES.txt
django_geventpool.egg-info/dependency_links.txt
django_geventpool.egg-info/requires.txt
django_geventpool.egg-info/top_level.txt
django_geventpool/backends/__init__.py
django_geventpool/backends/postgis/__init__.py
django_geventpool/backends/postgis/base.py
django_geventpool/backends/postgresql_psycopg2/__init__.py
django_geventpool/backends/postgresql_psycopg2/base.py
django_geventpool/backends/postgresql_psycopg2/creation.py
django_geventpool/backends/postgresql_psycopg2/exception.py
django_geventpool/backends/postgresql_psycopg2/psycopg2_pool.py
tests/__init__.py
tests/models.py
tests/tests.py