Metadata-Version: 1.1
Name: django-geventpool
Version: 1.2.1
Summary: Add a DB connection pool using gevent to django (based on django-db-geventpool)
Home-page: https://github.com/erickponce/django-db-geventpool
Author: Erick Ponce Leão
Author-email: erickponceleao@gmail.com
License: Apache 2.0
Platform: UNKNOWN
Classifier: Environment :: Web Environment
Classifier: Framework :: Django
Classifier: Intended Audience :: Developers
Classifier: License :: OSI Approved :: Apache Software License
Classifier: Operating System :: OS Independent
Classifier: Programming Language :: Python
Classifier: Programming Language :: Python :: 2
Classifier: Topic :: Software Development :: Libraries :: Application Frameworks
